jumpstarter_driver_tasmota/__init__.py
jumpstarter_driver_tasmota/driver.py
jumpstarter_driver_tasmota/driver_test.py
jumpstarter_driver_tasmota/py.typed
jumpstarter_driver_tasmota-0.7.4.dist-info/METADATA
jumpstarter_driver_tasmota-0.7.4.dist-info/WHEEL
jumpstarter_driver_tasmota-0.7.4.dist-info/entry_points.txt
jumpstarter_driver_tasmota-0.7.4.dist-info/RECORD
