Metadata-Version: 2.4
Name: jumpstarter-driver-tasmota
Version: 0.7.4
Summary: Jumpstarter driver for controlling Tasmota-compatible devices via MQTT
Project-URL: Homepage, https://jumpstarter.dev
Project-URL: source_archive, https://github.com/jumpstarter-dev/repo/archive/c5d38de69eadbb8eb0388bcfe3430a679fff0059.zip
Author-email: Nick Cao <nickcao@nichi.co>
License-Expression: Apache-2.0
Requires-Python: >=3.11
Requires-Dist: anyio>=4.10.0
Requires-Dist: jumpstarter-driver-power==0.7.4
Requires-Dist: jumpstarter==0.7.4
Requires-Dist: paho-mqtt>=2.1.0
